sky/__init__.py
sky/auth.py
sky/httpRequest.py
sky/sky.py
sky/utils.py
sky/exceptions/__init__.py
sky_api_python_client-0.4.2.dist-info/LICENSE
sky_api_python_client-0.4.2.dist-info/METADATA
sky_api_python_client-0.4.2.dist-info/WHEEL
sky_api_python_client-0.4.2.dist-info/top_level.txt
sky_api_python_client-0.4.2.dist-info/RECORD
