Metadata-Version: 2.1
Name: sky-api-python-client
Version: 0.4.2
Summary: Package for communicating with the Blackbaud Sky API
Home-page: https://github.com/LearnThinkCreate/sky-api-python-client
Author: Warren Hyson
Author-email: warren.hyson5@gmail.com
License: UNKNOWN
Platform: UNKNOWN
Classifier: Programming Language :: Python :: 3
Classifier: License :: OSI Approved :: GNU Lesser General Public License v3 or later (LGPLv3+)
Classifier: Operating System :: OS Independent
Requires-Python: >=3.8
License-File: LICENSE
Requires-Dist: requests
Requires-Dist: authlib
Requires-Dist: pandas
